[{"position":1,"photo":"228286.jpg","name":"Mendy","team_name":"CHE","position_name":"GKP","points":2,"special":""},{"position":2,"photo":"55459.jpg","name":"Cresswell","team_name":"WHU","position_name":"DEF","points":1,"special":""},{"position":3,"photo":"199249.jpg","name":"Reguil\u00f3n","team_name":"TOT","position_name":"DEF","points":2,"special":""},{"position":4,"photo":"111291.jpg","name":"Mar\u00e7al","team_name":"WOL","position_name":"DEF","points":3,"special":""},{"position":5,"photo":"220688.jpg","name":"Greenwood","team_name":"MUN","position_name":"MID","points":1,"special":""},{"position":6,"photo":"232185.jpg","name":"Sarr","team_name":"WAT","position_name":"MID","points":1,"special":""},{"position":7,"photo":"74208.jpg","name":"Pogba","team_name":"MUN","position_name":"MID","points":1,"special":"VC"},{"position":8,"photo":"172841.jpg","name":"Benrahma","team_name":"WHU","position_name":"MID","points":2,"special":""},{"position":9,"photo":"57531.jpg","name":"Antonio","team_name":"WHU","position_name":"FWD","points":2,"special":""},{"position":10,"photo":"14937.jpg","name":"Ronaldo","team_name":"MUN","position_name":"FWD","points":2,"special":"C"},{"position":11,"photo":"66749.jpg","name":"Lukaku","team_name":"CHE","position_name":"FWD","points":2,"special":""},{"position":12,"photo":"215059.jpg","name":"S\u00e1nchez","team_name":"BHA","position_name":"GKP","points":6,"special":""},{"position":13,"photo":"172632.jpg","name":"Gray","team_name":"EVE","position_name":"MID","points":2,"special":""},{"position":14,"photo":"214285.jpg","name":"Tsimikas","team_name":"LIV","position_name":"DEF","points":0,"special":""},{"position":15,"photo":"441191.jpg","name":"Livramento","team_name":"SOU","position_name":"DEF","points":4,"special":""}]